README.txt
setup.py
kontagent/__init__.py
kontagent/kontagent.py
kontagent/proxy.py
pykontagent.egg-info/PKG-INFO
pykontagent.egg-info/SOURCES.txt
pykontagent.egg-info/dependency_links.txt
pykontagent.egg-info/not-zip-safe
pykontagent.egg-info/requires.txt
pykontagent.egg-info/top_level.txt