Metadata-Version: 1.0
Name: pykontagent
Version: 0.3
Summary: A simple interface into the Kontagent REST API
Home-page: http://github.com/ericflo/pykontagent
Author: Eric Florenzano
Author-email: floguy@gmail.com
License: BSD
Keywords: kontagent,rest,api,client
Platform: UNKNOWN
Classifier: Programming Language :: Python
Classifier: Topic :: Software Development :: Libraries :: Python Modules
Classifier: Environment :: Web Environment
